{"name":"Influence Heat","sourceBook":"Mage: The Awakening","sourcePage":"162","primaryArcana":"Forces","arcanaRequirement":"Forces 1","requirements":[{"name":"Forces","dots":"1"}],"practice":"Compelling","action":"Instant","duration":"Prolonged (one scene)","aspect":"Covert","cost":"None","effect":"The mage can guide the direction and/or flow of existing heat. He could, for example, keep warm in cold weather by pulling the ambient warmth shed by other human bodies to himself, or make sure that the dim heat from a radiator on the other side of a bathroom reached the shower stall. He could not increase the temperature of the heat at this level, nor create heat where there is none.","rotes":[{"roteOrder":"Mysterium Rote","roteName":"Radiant Blessing","roteDicePool_Attribute":"Intelligence","roteDicePool_Skill":"Occult or Science","roteDescription":"The mages of the Mysterium like this rote because it allows them to keep their drafty old libraries from losing too much heat."}]}